Metadata-Version: 2.1
Name: class-filess
Version: 0.4
Summary: Удобный класс для работы с файлами
Author-email: masha22340@gmail.com
